ByteBunny/Byte.py
ByteBunny/__init__.py
bytebunny-1.0.0.dist-info/METADATA
bytebunny-1.0.0.dist-info/WHEEL
bytebunny-1.0.0.dist-info/top_level.txt
bytebunny-1.0.0.dist-info/RECORD
