Metadata-Version: 2.4
Name: ByteBunny
Version: 1.0.0
Summary: A modular package for registering custom scripts in Discord selfbots.
Author: DriizzyyB
Author-email: DriizzyyB <driizzyyboosts@gmail.com>
Project-URL: Homepage, https://github.com/driizzyy
Project-URL: Repository, https://github.com/driizzyy/ByteBunny-Module
Project-URL: Documentation, https://github.com/driizzyy/ByteBunny-Module#readme
Project-URL: Issues, https://github.com/driizzyy/ByteBunny-Module/issues
Keywords: discord,selfbot,modular,scripts,plugin
Classifier: Programming Language :: Python :: 3
Classifier: License :: OSI Approved :: MIT License
Classifier: Operating System :: OS Independent
Classifier: Intended Audience :: Developers
Classifier: Topic :: Software Development :: Libraries :: Python Modules
Requires-Python: >=3.8
Dynamic: author
